livy/__init__.py
livy/batch.py
livy/client.py
livy/models.py
livy/session.py
livy/utils.py
livy-0.8.0.dist-info/LICENSE
livy-0.8.0.dist-info/METADATA
livy-0.8.0.dist-info/WHEEL
livy-0.8.0.dist-info/top_level.txt
livy-0.8.0.dist-info/RECORD
