Metadata-Version: 2.1
Name: livy
Version: 0.8.0
Summary: A Python client for Apache Livy
Home-page: https://github.com/acroz/pylivy
Author: Andrew Crozier
Author-email: wacrozier@gmail.com
License: MIT
Platform: UNKNOWN
Classifier: License :: OSI Approved :: MIT License
Classifier: Programming Language :: Python :: 3
Classifier: Programming Language :: Python :: 3.6
Classifier: Programming Language :: Python :: 3.7
Classifier: Programming Language :: Python :: 3.8
Classifier: Programming Language :: Python :: 3.9
Requires-Dist: requests
Requires-Dist: pandas
Requires-Dist: dataclasses ; python_version < "3.7"
Provides-Extra: docs
Requires-Dist: sphinx ; extra == 'docs'
Requires-Dist: sphinx-autodoc-typehints ; extra == 'docs'
